ninjin/__init__.py
ninjin/decorator.py
ninjin/exceptions.py
ninjin/filtering.py
ninjin/logger.py
ninjin/ordering.py
ninjin/pagination.py
ninjin/pool.py
ninjin/resource.py
ninjin/schema.py
ninjin-0.2.0.dist-info/LICENSE
ninjin-0.2.0.dist-info/METADATA
ninjin-0.2.0.dist-info/WHEEL
ninjin-0.2.0.dist-info/top_level.txt
ninjin-0.2.0.dist-info/RECORD
